dtcc_wrangler/__init__.py
dtcc_wrangler/logging.py
dtcc_wrangler/register.py
dtcc_wrangler/city/__init__.py
dtcc_wrangler/city/enrich.py
dtcc_wrangler/city/modify.py
dtcc_wrangler/city/summarize.py
dtcc_wrangler/geometry/polygons.py
dtcc_wrangler/mesh/__init__.py
dtcc_wrangler/mesh/triangulate.py
dtcc_wrangler/pointcloud/__init__.py
dtcc_wrangler/pointcloud/classify.py
dtcc_wrangler/pointcloud/convert.py
dtcc_wrangler/pointcloud/filters.py
dtcc_wrangler/raster/__init__.py
dtcc_wrangler/raster/interpolation.py
dtcc_wrangler/raster/stats.py
dtcc_wrangler/roadnetwork/__init__.py
dtcc_wrangler/roadnetwork/graph.py
dtcc_wrangler-0.7.21.dist-info/LICENSE
dtcc_wrangler-0.7.21.dist-info/METADATA
dtcc_wrangler-0.7.21.dist-info/WHEEL
dtcc_wrangler-0.7.21.dist-info/top_level.txt
dtcc_wrangler-0.7.21.dist-info/RECORD
