Metadata-Version: 2.1
Name: dtcc-wrangler
Version: 0.7.21
Summary: DTCC Wrangler
Author-email: Anders Logg <logg@chalmers.se>, Vasilis Naserentin <vasilis.naserentin@chalmers.se>, Dag Wästberg <dwastberg@gmail.com>
Classifier: Intended Audience :: Science/Research
Classifier: Programming Language :: Python :: 3
Classifier: License :: OSI Approved :: MIT License
Requires-Python: >=3.10
License-File: LICENSE
Requires-Dist: numpy <2.0.0,>=1.20.0
Requires-Dist: scipy <2.0.0,>=1.6.0
Requires-Dist: shapely <3.0.0,>=2.0.0
Requires-Dist: rasterio <2.0.0,>=1.2.0
Requires-Dist: rasterstats <1.0.0,>=0.19.0
Requires-Dist: pypoints2grid <0.2.0,>=0.1.9
Requires-Dist: dtcc-model >=0.7.21
Requires-Dist: dtcc-io >=0.7.21
Requires-Dist: dtcc-common >=0.7.21
Provides-Extra: test
Requires-Dist: pytest ; extra == 'test'
